simples_matlib/__init__.py
simples_matlib/simples_matlib.py
simples_matlib-0.2.2.dist-info/METADATA
simples_matlib-0.2.2.dist-info/WHEEL
simples_matlib-0.2.2.dist-info/top_level.txt
simples_matlib-0.2.2.dist-info/RECORD
