Metadata-Version: 2.1
Name: simples_matlib
Version: 0.2.2
Summary: Uma simples biblioteca para criar gráficos usando matplotlib
Home-page: https://github.com/antonioanerao/simples_matlib
Author: Antonio Anerão
Author-email: anerao.junior@gmail.com
Classifier: Programming Language :: Python :: 3
Classifier: License :: OSI Approved :: MIT License
Classifier: Operating System :: OS Independent
Requires-Python: >=3.6
Requires-Dist: matplotlib
Requires-Dist: numpy
